yfinance_exporter.py
yfinance_exporter-1.1.0.dist-info/METADATA
yfinance_exporter-1.1.0.dist-info/WHEEL
yfinance_exporter-1.1.0.dist-info/RECORD
