Metadata-Version: 2.3
Name: yfinance-exporter
Version: 1.1.0
Summary: 
Requires-Python: >=3.13
Classifier: Programming Language :: Python :: 3
Classifier: Programming Language :: Python :: 3.13
Requires-Dist: daemon-metrics (>=1.0.0,<2.0.0)
Requires-Dist: prometheus-client (>=0.21.1)
Requires-Dist: the-conf (>=1.0.4)
Requires-Dist: yfinance (>=0.2.51)
